lottery/__init__.py
lottery/daletou.py
lottery/util.py
python_lottery-0.7.dist-info/LICENSE
python_lottery-0.7.dist-info/METADATA
python_lottery-0.7.dist-info/WHEEL
python_lottery-0.7.dist-info/top_level.txt
python_lottery-0.7.dist-info/RECORD
