Metadata-Version: 2.1
Name: python-lottery
Version: 0.7
License-File: LICENSE
Requires-Dist: selenium (>=4.11.2)
Requires-Dist: webdriver-manager (>=4.0.0)
Requires-Dist: pandas (>=2.0.3)
Requires-Dist: numpy (>=1.24.3)
Requires-Dist: statsmodels (>=0.14.0)
Requires-Dist: Pillow (>=9.5.0)
Requires-Dist: scikit-learn (>=1.3.2)
Requires-Dist: pmdarima (>=2.0.4)
Requires-Dist: requests
Requires-Dist: twine
